A06/float.v
module rom_8 (
    input [2:0] addr,
    input OE,
    output reg [31:0] out
);

    reg [31:0] data [7:0];

    initial begin
        data[0] = 32'h0986ab68;
        data[1] = 32'h10385ba9;
        data[2] = 32'b0_01111111_00000000000000000000000; //1 decimal
        data[3] = 32'b0_01111101_00000000000000000000000; //0.01 binario = 0,25 decimal
        data[4] = 32'b0_10000000_10000000000000000000000; //3 decimal
        data[5] = 32'b0_10000010_01000000000000000000000; //10 decimal
        data[6] = 32'b0_01111101_01000000000000000000000; //0.3125 decimal
        data[7] = 32'b0_01111110_11000000000000000000000; //0.875 decimal
    end

    always @(addr, OE) begin
        if (OE == 1'b1)
            out = data[addr];
        else
            out = 32'bz;
    end

endmodule


module ram_4 (
    input [31:0] in,
    input [1:0] addr,
    input RW, OE,
    output reg [31:0] out
);

    reg [31:0] data [3:0];

    always @(in, addr, RW, OE) begin
        if (RW == 1'b0 && OE == 1'b1)
            out = data[addr];
        else
            out = 32'bz;
        
        if (RW == 1'b1)
            data[addr] = in;
    end
endmodule

//fpa module will read two rom values, use adder module to add them and put the result in ram module
//ram_RW = 1 - write, 0 - read
module fpa(ram_addr, ram_out, done);
    input [1:0] ram_addr;
    output reg done;
    output [31:0] ram_out;

    reg clk = 1'b1;
    always #1 clk = ~clk;

    reg [2:0] rom_addr = 3'b000;
    wire [31:0] ram_in;
    wire [1:0] ram_addr_mux;
    wire [31:0] rom_out1, rom_out2;
    reg ram_RW;
    reg rom_OE;
    reg ram_OE;
    reg adder_en;
    reg [1:0] addr_counter;

    assign ram_addr_mux = (ram_RW ? addr_counter : ram_addr);

    rom_8 rom1 (.addr(rom_addr), .OE(rom_OE), .out(rom_out1));
    rom_8 rom2 (.addr(rom_addr + 1'b1), .OE(rom_OE), .out(rom_out2));
    ram_4 ram (.in(ram_in), .addr(ram_addr_mux), .RW(ram_RW), .OE(ram_OE), .out(ram_out));
    adder adder (.operand_1(rom_out1), .operand_2(rom_out2), .clk(clk), .en(adder_en), .sum(ram_in));

    initial begin
        rom_addr = 3'b000;
        addr_counter = 2'b00;
        rom_OE = 1'b1;

        for (addr_counter = 2'b00; addr_counter < 2'b11 ; addr_counter = addr_counter + 1'b1) begin
            adder_en = 1'b1;
            ram_RW = 1'b1;
            #50 rom_addr = rom_addr + 2'b10;
            #50 ram_RW = 1'b0;
            #50 adder_en = 1'b0;
        end
        done = 1'b1;
        ram_OE = 1'b1;
        ram_RW = 1'b0;
    end

endmodule


//=================================================================================================================================================================================================
//This module compares the exponent of both inputs and shifts the mantissa of the smaller number to make the exponents equal.
module compandshift(
  input [23:0] cas_mantissa_1, cas_mantissa_2,
  input [7:0] cas_exponent_1, cas_exponent_2,
  input clk, reset,
  output reg [23:0] cas_shifted_mantissa_1, cas_shifted_mantissa_2,
  output reg [7:0] cas_new_exponent,
  output reg done_1=0
);
  reg [7:0] diff;
  always @(posedge clk)
  begin
      if(cas_exponent_1 == cas_exponent_2)
      begin
          cas_shifted_mantissa_1<=cas_mantissa_1;
          cas_shifted_mantissa_2<=cas_mantissa_2;
          cas_new_exponent<=cas_exponent_1+1'b1;
          done_1<=1;
      end
      else if(cas_exponent_1>cas_exponent_2)
      begin
          diff=cas_exponent_1-cas_exponent_2;
          cas_shifted_mantissa_1<=cas_mantissa_1;
          cas_shifted_mantissa_2<=(cas_mantissa_2>>diff);
          cas_new_exponent<=cas_exponent_1+1'b1;
          done_1<=1;
      end
      else if(cas_exponent_2>cas_exponent_1)
      begin
          diff=cas_exponent_2-cas_exponent_1;
          cas_shifted_mantissa_2<=cas_mantissa_2;
          cas_shifted_mantissa_1<=(cas_mantissa_1>>diff);
          cas_new_exponent<=cas_exponent_2+1'b1;
          done_1<=1;
      end
  end
endmodule

//=============================================================================================================================================================================================
//This module adds shifted mantissas
module addition(
  input [23:0] shifted_mantissa_1,
  input [23:0] shifted_mantissa_2,
  input [7:0] tmp_new_exponent,
  input clk,reset,
  output reg [24:0] mantissa_sum,
  output reg [7:0] add_new_exponent,
  output reg done_2=0
);
  always @(posedge clk)
  begin
      mantissa_sum<=shifted_mantissa_1+shifted_mantissa_2;
      add_new_exponent<=tmp_new_exponent;
      if(mantissa_sum==(shifted_mantissa_1+shifted_mantissa_2))
      begin
          done_2<=1;
      end
  end
endmodule

//==============================================================================================================================================================================================
//This module normalises the output mantissa
module normalisation(
  input [24:0] mantissa_sum,
  input [7:0] new_exponent,
  input clk,reset,
  output reg [23:0] mantissa_final,
  output reg [7:0] exponent_final,
  output reg done_3=0
);
  reg rst=0;
  always @(posedge clk)
  begin
      if(rst==0)
      begin
          mantissa_final<=mantissa_sum[24:1];
          exponent_final<=new_exponent;
          if(mantissa_final==mantissa_sum[24:1])
          begin
              rst<=1;
          end
      end
      else begin
          repeat(24) begin
              if(mantissa_final[23]==0)
              begin
                  mantissa_final<=(mantissa_final<<1'b1);
                  exponent_final<=exponent_final-1'b1;
              end
              else begin
                  done_3<=1;
                  rst<=0;
              end
          end
    end
end
endmodule
//=====================================================================================================================================================================================

module adder(
  input [31:0] operand_1, operand_2,
  input clk, en,
  output reg [31:0] sum = 32'bz
);
  wire reset;
  reg  busy_1=0, busy_2=0, busy_3=0;
  reg  [7:0]  exponent_1, exponent_2, new_exponent, tmp_new_exponent;
  reg  [23:0] mantissa_1, mantissa_2, shifted_mantissa_1, shifted_mantissa_2;
  wire [7:0]  exponent_final, add_new_exponent, cas_new_exponent;
  wire [23:0] mantissa_final, cas_shifted_mantissa_1, cas_shifted_mantissa_2;
  reg  [24:0] mantissa_sum;
  wire [24:0] add_mantissa_sum;

  compandshift cas(mantissa_1,mantissa_2,exponent_1,exponent_2,clk,reset,cas_shifted_mantissa_1,cas_shifted_mantissa_2,cas_new_exponent,done_1);
  addition add(shifted_mantissa_1,shifted_mantissa_2,tmp_new_exponent,clk,reset,add_mantissa_sum,add_new_exponent,done_2); 
  normalisation normalise(mantissa_sum,new_exponent,clk,reset,mantissa_final,exponent_final,done_3);

  always @(posedge clk)
  begin
      if (operand_1 === 32'b0)
      begin
        sum <= operand_2;
      end
      else if (operand_2 === 32'b0)
      begin
        sum <= operand_1;
      end

      else if(busy_1==0 & en==1)
      begin
          exponent_1<=operand_1[30:23];
          exponent_2<=operand_2[30:23];
          mantissa_1<={1'b1,operand_1[22:0]};
          mantissa_2<={1'b1,operand_2[22:0]};
          busy_1<=1;    
      end
      else if (done_1==1 && busy_2==0)
      begin
          shifted_mantissa_1<=cas_shifted_mantissa_1;
          shifted_mantissa_2<=cas_shifted_mantissa_2;
          tmp_new_exponent<=cas_new_exponent;
          busy_1<=0;
          busy_2<=1;
      end
      else if(done_2==1 && busy_3==0)
      begin
          mantissa_sum <= add_mantissa_sum;
          new_exponent <= add_new_exponent;
          busy_2<=0;
          busy_3<=1;
      end
      else if(done_3==1)
      begin
          sum<={operand_1[31],exponent_final,mantissa_final[22:0]};
          busy_3<=0;
          $display("sum:%b",sum);
      end
  end
endmodule


//write a testbench for the fpa module to gtk wave
module fpa_tb;
    reg clk;
    wire done;
    wire [31:0] ram_out;
    reg [1:0] ram_addr;
    fpa fpa1(ram_addr, ram_out, done);
    initial begin
        clk = 1'b0;
        forever #1 clk = ~clk;
    end
    initial begin
        $dumpfile("fpa_tb.vcd");
        $dumpvars(0, fpa_tb);
        #500 $finish;
    end
endmodule

A06/fpa_tb.vcd
$date
	Wed Apr 03 12:41:18 2024
$end
$version
	Icarus Verilog
$end
$timescale
	1s
$end
$scope module fpa_tb $end
$var wire 32 ! ram_out [31:0] $end
$var wire 1 " done $end
$var reg 1 # clk $end
$var reg 2 $ ram_addr [1:0] $end
$scope module fpa1 $end
$var wire 2 % ram_addr [1:0] $end
$var wire 32 & rom_out2 [31:0] $end
$var wire 32 ' rom_out1 [31:0] $end
$var wire 32 ( ram_out [31:0] $end
$var wire 32 ) ram_in [31:0] $end
$var wire 2 * ram_addr_mux [1:0] $end
$var reg 1 + adder_en $end
$var reg 2 , addr_counter [1:0] $end
$var reg 1 - clk $end
$var reg 1 " done $end
$var reg 1 . ram_OE $end
$var reg 1 / ram_RW $end
$var reg 1 0 rom_OE $end
$var reg 3 1 rom_addr [2:0] $end
$scope module adder $end
$var wire 1 - clk $end
$var wire 1 + en $end
$var wire 1 2 reset $end
$var wire 32 3 operand_2 [31:0] $end
$var wire 32 4 operand_1 [31:0] $end
$var wire 24 5 mantissa_final [23:0] $end
$var wire 8 6 exponent_final [7:0] $end
$var wire 1 7 done_3 $end
$var wire 1 8 done_2 $end
$var wire 1 9 done_1 $end
$var wire 24 : cas_shifted_mantissa_2 [23:0] $end
$var wire 24 ; cas_shifted_mantissa_1 [23:0] $end
$var wire 8 < cas_new_exponent [7:0] $end
$var wire 8 = add_new_exponent [7:0] $end
$var wire 25 > add_mantissa_sum [24:0] $end
$var reg 1 ? busy_1 $end
$var reg 1 @ busy_2 $end
$var reg 1 A busy_3 $end
$var reg 8 B exponent_1 [7:0] $end
$var reg 8 C exponent_2 [7:0] $end
$var reg 24 D mantissa_1 [23:0] $end
$var reg 24 E mantissa_2 [23:0] $end
$var reg 25 F mantissa_sum [24:0] $end
$var reg 8 G new_exponent [7:0] $end
$var reg 24 H shifted_mantissa_1 [23:0] $end
$var reg 24 I shifted_mantissa_2 [23:0] $end
$var reg 32 J sum [31:0] $end
$var reg 8 K tmp_new_exponent [7:0] $end
$scope module add $end
$var wire 1 - clk $end
$var wire 1 2 reset $end
$var wire 24 L shifted_mantissa_1 [23:0] $end
$var wire 24 M shifted_mantissa_2 [23:0] $end
$var wire 8 N tmp_new_exponent [7:0] $end
$var reg 8 O add_new_exponent [7:0] $end
$var reg 1 8 done_2 $end
$var reg 25 P mantissa_sum [24:0] $end
$upscope $end
$scope module cas $end
$var wire 8 Q cas_exponent_1 [7:0] $end
$var wire 8 R cas_exponent_2 [7:0] $end
$var wire 24 S cas_mantissa_1 [23:0] $end
$var wire 24 T cas_mantissa_2 [23:0] $end
$var wire 1 - clk $end
$var wire 1 2 reset $end
$var reg 8 U cas_new_exponent [7:0] $end
$var reg 24 V cas_shifted_mantissa_1 [23:0] $end
$var reg 24 W cas_shifted_mantissa_2 [23:0] $end
$var reg 8 X diff [7:0] $end
$var reg 1 9 done_1 $end
$upscope $end
$scope module normalise $end
$var wire 1 - clk $end
$var wire 25 Y mantissa_sum [24:0] $end
$var wire 8 Z new_exponent [7:0] $end
$var wire 1 2 reset $end
$var reg 1 7 done_3 $end
$var reg 8 [ exponent_final [7:0] $end
$var reg 24 \ mantissa_final [23:0] $end
$var reg 1 ] rst $end
$upscope $end
$upscope $end
$scope module ram $end
$var wire 1 . OE $end
$var wire 1 / RW $end
$var wire 2 ^ addr [1:0] $end
$var wire 32 _ in [31:0] $end
$var reg 32 ` out [31:0] $end
$upscope $end
$scope module rom1 $end
$var wire 1 0 OE $end
$var wire 3 a addr [2:0] $end
$var reg 32 b out [31:0] $end
$upscope $end
$scope module rom2 $end
$var wire 1 0 OE $end
$var wire 3 c addr [2:0] $end
$var reg 32 d out [31:0] $end
$upscope $end
$upscope $end
$upscope $end
$enddefinitions $end
$comment Show the parameter values. $end
$dumpall
$end
#0
$dumpvars
b10000001110000101101110101001 d
b1 c
b1001100001101010101101101000 b
b0 a
bz `
bz _
b0 ^
0]
bx \
bx [
bx Z
bx Y
bx X
bx W
bx V
bx U
b1xxxxxxxxxxxxxxxxxxxxxxx T
b1xxxxxxxxxxxxxxxxxxxxxxx S
bx R
bx Q
bx P
bx O
bx N
bx M
bx L
bx K
bz J
bx I
bx H
bx G
bx F
b1xxxxxxxxxxxxxxxxxxxxxxx E
b1xxxxxxxxxxxxxxxxxxxxxxx D
bx C
bx B
0A
0@
1?
bx >
bx =
bx <
bx ;
bx :
09
08
07
bx 6
bx 5
b1001100001101010101101101000 4
b10000001110000101101110101001 3
z2
b0 1
10
1/
x.
1-
b0 ,
1+
b0 *
bz )
bz (
b1001100001101010101101101000 '
b10000001110000101101110101001 &
bx %
bx $
0#
x"
bz !
$end
#1
1#
0-
#2
0#
1-
#3
1#
0-
#4
0#
1-
#5
1#
0-
#6
0#
1-
#7
1#
0-
#8
0#
1-
#9
1#
0-
#10
0#
1-
#11
1#
0-
#12
0#
1-
#13
1#
0-
#14
0#
1-
#15
1#
0-
#16
0#
1-
#17
1#
0-
#18
0#
1-
#19
1#
0-
#20
0#
1-
#21
1#
0-
#22
0#
1-
#23
1#
0-
#24
0#
1-
#25
1#
0-
#26
0#
1-
#27
1#
0-
#28
0#
1-
#29
1#
0-
#30
0#
1-
#31
1#
0-
#32
0#
1-
#33
1#
0-
#34
0#
1-
#35
1#
0-
#36
0#
1-
#37
1#
0-
#38
0#
1-
#39
1#
0-
#40
0#
1-
#41
1#
0-
#42
0#
1-
#43
1#
0-
#44
0#
1-
#45
1#
0-
#46
0#
1-
#47
1#
0-
#48
0#
1-
#49
1#
0-
#50
b111110100000000000000000000000 &
b111110100000000000000000000000 3
b111110100000000000000000000000 d
b111111100000000000000000000000 '
b111111100000000000000000000000 4
b111111100000000000000000000000 b
0#
1-
b11 c
b10 1
b10 a
#51
1#
0-
#52
0#
1-
#53
1#
0-
#54
0#
1-
#55
1#
0-
#56
0#
1-
#57
1#
0-
#58
0#
1-
#59
1#
0-
#60
0#
1-
#61
1#
0-
#62
0#
1-
#63
1#
0-
#64
0#
1-
#65
1#
0-
#66
0#
1-
#67
1#
0-
#68
0#
1-
#69
1#
0-
#70
0#
1-
#71
1#
0-
#72
0#
1-
#73
1#
0-
#74
0#
1-
#75
1#
0-
#76
0#
1-
#77
1#
0-
#78
0#
1-
#79
1#
0-
#80
0#
1-
#81
1#
0-
#82
0#
1-
#83
1#
0-
#84
0#
1-
#85
1#
0-
#86
0#
1-
#87
1#
0-
#88
0#
1-
#89
1#
0-
#90
0#
1-
#91
1#
0-
#92
0#
1-
#93
1#
0-
#94
0#
1-
#95
1#
0-
#96
0#
1-
#97
1#
0-
#98
0#
1-
#99
1#
0-
#100
bx *
bx ^
0#
1-
0/
#101
1#
0-
#102
0#
1-
#103
1#
0-
#104
0#
1-
#105
1#
0-
#106
0#
1-
#107
1#
0-
#108
0#
1-
#109
1#
0-
#110
0#
1-
#111
1#
0-
#112
0#
1-
#113
1#
0-
#114
0#
1-
#115
1#
0-
#116
0#
1-
#117
1#
0-
#118
0#
1-
#119
1#
0-
#120
0#
1-
#121
1#
0-
#122
0#
1-
#123
1#
0-
#124
0#
1-
#125
1#
0-
#126
0#
1-
#127
1#
0-
#128
0#
1-
#129
1#
0-
#130
0#
1-
#131
1#
0-
#132
0#
1-
#133
1#
0-
#134
0#
1-
#135
1#
0-
#136
0#
1-
#137
1#
0-
#138
0#
1-
#139
1#
0-
#140
0#
1-
#141
1#
0-
#142
0#
1-
#143
1#
0-
#144
0#
1-
#145
1#
0-
#146
0#
1-
#147
1#
0-
#148
0#
1-
#149
1#
0-
#150
b1 *
b1 ^
0#
1-
1/
b1 ,
1+
#151
1#
0-
#152
0#
1-
#153
1#
0-
#154
0#
1-
#155
1#
0-
#156
0#
1-
#157
1#
0-
#158
0#
1-
#159
1#
0-
#160
0#
1-
#161
1#
0-
#162
0#
1-
#163
1#
0-
#164
0#
1-
#165
1#
0-
#166
0#
1-
#167
1#
0-
#168
0#
1-
#169
1#
0-
#170
0#
1-
#171
1#
0-
#172
0#
1-
#173
1#
0-
#174
0#
1-
#175
1#
0-
#176
0#
1-
#177
1#
0-
#178
0#
1-
#179
1#
0-
#180
0#
1-
#181
1#
0-
#182
0#
1-
#183
1#
0-
#184
0#
1-
#185
1#
0-
#186
0#
1-
#187
1#
0-
#188
0#
1-
#189
1#
0-
#190
0#
1-
#191
1#
0-
#192
0#
1-
#193
1#
0-
#194
0#
1-
#195
1#
0-
#196
0#
1-
#197
1#
0-
#198
0#
1-
#199
1#
0-
#200
b1000001001000000000000000000000 &
b1000001001000000000000000000000 3
b1000001001000000000000000000000 d
b1000000010000000000000000000000 '
b1000000010000000000000000000000 4
b1000000010000000000000000000000 b
0#
1-
b101 c
b100 1
b100 a
#201
1#
0-
#202
0#
1-
#203
1#
0-
#204
0#
1-
#205
1#
0-
#206
0#
1-
#207
1#
0-
#208
0#
1-
#209
1#
0-
#210
0#
1-
#211
1#
0-
#212
0#
1-
#213
1#
0-
#214
0#
1-
#215
1#
0-
#216
0#
1-
#217
1#
0-
#218
0#
1-
#219
1#
0-
#220
0#
1-
#221
1#
0-
#222
0#
1-
#223
1#
0-
#224
0#
1-
#225
1#
0-
#226
0#
1-
#227
1#
0-
#228
0#
1-
#229
1#
0-
#230
0#
1-
#231
1#
0-
#232
0#
1-
#233
1#
0-
#234
0#
1-
#235
1#
0-
#236
0#
1-
#237
1#
0-
#238
0#
1-
#239
1#
0-
#240
0#
1-
#241
1#
0-
#242
0#
1-
#243
1#
0-
#244
0#
1-
#245
1#
0-
#246
0#
1-
#247
1#
0-
#248
0#
1-
#249
1#
0-
#250
bx *
bx ^
0#
1-
0/
#251
1#
0-
#252
0#
1-
#253
1#
0-
#254
0#
1-
#255
1#
0-
#256
0#
1-
#257
1#
0-
#258
0#
1-
#259
1#
0-
#260
0#
1-
#261
1#
0-
#262
0#
1-
#263
1#
0-
#264
0#
1-
#265
1#
0-
#266
0#
1-
#267
1#
0-
#268
0#
1-
#269
1#
0-
#270
0#
1-
#271
1#
0-
#272
0#
1-
#273
1#
0-
#274
0#
1-
#275
1#
0-
#276
0#
1-
#277
1#
0-
#278
0#
1-
#279
1#
0-
#280
0#
1-
#281
1#
0-
#282
0#
1-
#283
1#
0-
#284
0#
1-
#285
1#
0-
#286
0#
1-
#287
1#
0-
#288
0#
1-
#289
1#
0-
#290
0#
1-
#291
1#
0-
#292
0#
1-
#293
1#
0-
#294
0#
1-
#295
1#
0-
#296
0#
1-
#297
1#
0-
#298
0#
1-
#299
1#
0-
#300
b10 *
b10 ^
0#
1-
1/
b10 ,
1+
#301
1#
0-
#302
0#
1-
#303
1#
0-
#304
0#
1-
#305
1#
0-
#306
0#
1-
#307
1#
0-
#308
0#
1-
#309
1#
0-
#310
0#
1-
#311
1#
0-
#312
0#
1-
#313
1#
0-
#314
0#
1-
#315
1#
0-
#316
0#
1-
#317
1#
0-
#318
0#
1-
#319
1#
0-
#320
0#
1-
#321
1#
0-
#322
0#
1-
#323
1#
0-
#324
0#
1-
#325
1#
0-
#326
0#
1-
#327
1#
0-
#328
0#
1-
#329
1#
0-
#330
0#
1-
#331
1#
0-
#332
0#
1-
#333
1#
0-
#334
0#
1-
#335
1#
0-
#336
0#
1-
#337
1#
0-
#338
0#
1-
#339
1#
0-
#340
0#
1-
#341
1#
0-
#342
0#
1-
#343
1#
0-
#344
0#
1-
#345
1#
0-
#346
0#
1-
#347
1#
0-
#348
0#
1-
#349
1#
0-
#350
b111111011000000000000000000000 &
b111111011000000000000000000000 3
b111111011000000000000000000000 d
b111110101000000000000000000000 '
b111110101000000000000000000000 4
b111110101000000000000000000000 b
0#
1-
b111 c
b110 1
b110 a
