EP02/calculadora.v
module calculadora 
#(parameter W = 32) (
    input clock, reset, opera,
    input [4:0] read,
    output [W-1:0] data
);

wire [31:0] romOut;
wire [W-1:0] regOut1, regOut2;
wire [W-1:0] AluBMUX, AluOut;
wire [4:0] regRead1Mux;

reg [$clog2(16)-1:0] romAddr = 0;
reg romOE = 1'b1;

assign data = regOut1;
assign AluBMUX = romOut[5] ? regOut2 : romOut[31:20];
assign regRead1Mux = opera ? romOut[19:15] : read;

registerfile #(W) rf (
    .Read1(regRead1Mux),
    .Read2(romOut[24:20]),
    .WriteReg(romOut[11:7]),
    .WriteData(AluOut),
    .RegWrite(opera),
    .Data1(regOut1),
    .Data2(regOut2),
    .clock(clock)
);

alu #(W) alu (
    .ALUctl(AluCtl),
    .A(regOut1),
    .B(AluBMUX),
    .ALUout(AluOut),
    .Zero(),
    .Overflow()
);

rom #(32, 16) rom (
    .address(romAddr),
    .oe(romOE),
    .data(romOut)
);



reg [3:0] AluCtl;
localparam AandB = 4'b0000;
localparam AorB = 4'b0001;
localparam AplusB = 4'b0010;
localparam AminusB = 4'b0110;
localparam AlessthanB = 4'b0111;
localparam AnorB = 4'b1100;


initial begin
    romAddr = 0;
    romOE = 1;
end

always @(posedge clock or reset) begin
    if(reset) begin
        romAddr <= 0;
        romOE <= 1;
    end
    else begin
        if(opera && romAddr < 16) begin
            romAddr <= romAddr + 1;
        end
        else begin

        end
    end
end

always @(romOut) begin
    if(romOut[5] == 1) begin
        case(romOut[14:12])
            3'b000: begin 
                if (romOut[30] == 0) begin
                    AluCtl = AplusB;
                end
                else begin
                    AluCtl = AminusB;
                end
            end
            3'b110: AluCtl = AorB;
            3'b111: AluCtl = AandB;
            3'b010: AluCtl = AlessthanB;
        endcase
    end
    if(romOut[5] == 0) begin
        case(romOut[14:12])
            3'b000: AluCtl = AplusB;
            3'b110: AluCtl = AorB;
            3'b111: AluCtl = AandB;
            3'b010: AluCtl = AlessthanB;
        endcase
    end
end

endmodule
//registerfile ========================================================================

module registerfile
    #(parameter W = 32)
    (  input [4:0] Read1, Read2, WriteReg,
       input [W-1:0] WriteData,
       input RegWrite,
       output [W-1:0] Data1, Data2,
       input clock
    );

reg [W-1:0] regfile[31:0];


initial begin
    regfile[0] = 32'b0;
end

assign Data1 = regfile[Read1];
assign Data2 = regfile[Read2];

always @(posedge clock) begin
    if (RegWrite && (WriteReg != 4'b0000)) begin
        regfile[WriteReg] = WriteData;
    end
end
endmodule

//ULA ===================================================================================
module alu
#(parameter W = 32)
(
    input [3:0] ALUctl,
    input [W-1:0] A, B,
    output [W-1:0] ALUout,
    output Overflow, Zero
);

    reg [W-1:0] outreg;
    reg overf;
    assign Zero = (ALUout == 0);
    assign ALUout = outreg;
    assign Overflow = (ALUctl == 4'b0010) ? ((A[W-1] == B[W-1] && A[W-1] != outreg[W-1])) ? 1 : 0 : ((A[W-1] != B[W-1] && A[W-1] != outreg[W-1])) ? 1 : 0;
    always @(*) begin
        case (ALUctl)
            4'b0000: outreg = A & B; // AND operation
            4'b0001: outreg = A | B; // OR operation
            4'b0010: outreg = A + B; // Addition
            4'b0110: outreg = A-B; // Subtraction
            4'b0111: outreg = $signed(A) < $signed(B); // Less than
            4'b1100: outreg = ~(A | B); // NOR operation
        endcase
    end
endmodule

//Testbench ===================================================================================
module calculadora_tb;

  localparam W = 32;  // Teste com Ws diferentes!

  reg          reset, opera, clock = 0;
  reg  [4:0]   read;
  wire [W-1:0] data;
  
  calculadora #(W) dut(.*);

  always #1 clock = ~clock;

  initial begin
    
    $dumpfile ("calculadora_tb2.vcd");
    $dumpvars(0, calculadora_tb);

    read <= 1'b0;
    opera <= 1'b0;
    reset <= 1'b1;
    #1 reset <= 1'b0;

    #3;

    // Teste instrução 1 -> addi x0, x0, 1     00100013
    opera <= 1'b1; #2; opera <= 1'b0;
    read <= 0;
    #1 if (data==0)
      $display("Acerto: RF[%d] = %h, esperado 0.", read, data);
    else
      $display("Erro: RF[%d] = %h, esperado 0.", read, data);

    opera <= 1'b1; #2; opera <= 1'b0;
    read <= 1;
    #1 if (data==1)
      $display("Acerto: RF[%d] = %h, esperado 1.", read, data);
    else
      $display("Erro: RF[%d] = %h, esperado 1.", read, data);

    opera <= 1'b1; #2; opera <= 1'b0;
    read <= 1;
    #1 if (data==2)
      $display("Acerto: RF[%d] = %h, esperado 2.", read, data);
    else
      $display("Erro: RF[%d] = %h, esperado 2.", read, data);


    opera <= 1'b1; #2; opera <= 1'b0;
    read <= 2;
    #1 if (data==2)
      $display("Acerto: RF[%d] = %h, esperado 2.", read, data);
    else
      $display("Erro: RF[%d] = %h, esperado 2.", read, data);

    opera <= 1'b1; #2; opera <= 1'b0;
    read <= 3;
    #1 if (data==4)
      $display("Acerto: RF[%d] = %h, esperado 4.", read, data);
    else
      $display("Erro: RF[%d] = %h, esperado 4.", read, data);

    opera <= 1'b1; #2; opera <= 1'b0;
    read <= 4;
    #1 if (data==1)
      $display("Acerto: RF[%d] = %h, esperado 1.", read, data);
    else
      $display("Erro: RF[%d] = %h, esperado 1.", read, data);


    opera <= 1'b1; #2; opera <= 1'b0;
    read <= 5;
    #1 if (data==3)
      $display("Acerto: RF[%d] = %h, esperado 3.", read, data);
    else
      $display("Erro: RF[%d] = %h, esperado 3.", read, data);


    opera <= 1'b1; #2; opera <= 1'b0;
    read <= 6;
    #1 if (data==7)
      $display("Acerto: RF[%d] = %h, esperado 7.", read, data);
    else
      $display("Erro: RF[%d] = %h, esperado 7.", read, data);

    opera <= 1'b1; #2; opera <= 1'b0;
    read <= 7;
    #1 if (data==1)
      $display("Acerto: RF[%d] = %h, esperado 1.", read, data);
    else
      $display("Erro: RF[%d] = %h, esperado 1.", read, data);


    opera <= 1'b1; #2; opera <= 1'b0;
    read <= 7;
    #1 if (data==4095)
      $display("Acerto: RF[%d] = %h, esperado 0x00000fff.", read, data);
    else
      $display("Erro: RF[%d] = %h, esperado 0x00000fff.", read, data);


    opera <= 1'b1; #2; opera <= 1'b0;
    read <= 8;
    #1 if (data==0)
      $display("Acerto: RF[%d] = %h, esperado 0.", read, data);
    else
      $display("Erro: RF[%d] = %h, esperado 0.", read, data);


    opera <= 1'b1; #2; opera <= 1'b0;
    read <= 9;
    #1 if (data==1)
      $display("Acerto: RF[%d] = %h, esperado 1.", read, data);
    else
      $display("Erro: RF[%d] = %h, esperado 1.", read, data);


    opera <= 1'b1; #2; opera <= 1'b0;
    read <= 10;
    #1 if (data==4096)
      $display("Acerto: RF[%d] = %h, esperado 0x00001000.", read, data);
    else
      $display("Erro: RF[%d] = %h, esperado 0x00001000.", read, data);


    opera <= 1'b1; #2; opera <= 1'b0;
    read <= 10;
    #1 if (data==4096)
      $display("Acerto: RF[%d] = %h, esperado 0x00001000.", read, data);
    else
      $display("Erro: RF[%d] = %h, esperado 0x00001000.", read, data);

    opera <= 1'b1; #2; opera <= 1'b0;
    read <= 10;
    #1 if (data==1)
      $display("Acerto: RF[%d] = %h, esperado 1.", read, data);
    else
      $display("Erro: RF[%d] = %h, esperado 1.", read, data);

    opera <= 1'b1; #2; opera <= 1'b0;
    read <= 10;
    #1 if (data== -4094)
      $display("Acerto: RF[%d] = %h, esperado 0xfffff002.", read, data);
    else
      $display("Erro: RF[%d] = %h, esperado 0xfffff002.", read, data);

    $finish;
  end
endmodule

module rom
    #( parameter W = 32,
       parameter L = 16)
     ( input  [$clog2(L)-1:0] address,
       input  oe,
       output [W-1:0] data
     );

    reg [W-1:0] mem[L-1:0];
    
    assign data = (oe) ? mem[address] : {W{1'bZ}};

    initial begin
        $readmemh("rom.hex",mem,0,L-1);
    end
endmodule

EP02/calculadora_tb2.vcd
$date
	Sat Apr 20 23:55:08 2024
$end
$version
	Icarus Verilog
$end
$timescale
	1s
$end
$scope module calculadora_tb $end
$var wire 32 ! data [31:0] $end
$var parameter 32 " W $end
$var reg 1 # clock $end
$var reg 1 $ opera $end
$var reg 5 % read [4:0] $end
$var reg 1 & reset $end
$scope module dut $end
$var wire 1 # clock $end
$var wire 32 ' data [31:0] $end
$var wire 1 $ opera $end
$var wire 5 ( read [4:0] $end
$var wire 1 & reset $end
$var wire 32 ) romOut [31:0] $end
$var wire 5 * regRead1Mux [4:0] $end
$var wire 32 + regOut2 [31:0] $end
$var wire 32 , regOut1 [31:0] $end
$var wire 32 - AluOut [31:0] $end
$var wire 32 . AluBMUX [31:0] $end
$var parameter 4 / AandB $end
$var parameter 4 0 AlessthanB $end
$var parameter 4 1 AminusB $end
$var parameter 4 2 AnorB $end
$var parameter 4 3 AorB $end
$var parameter 4 4 AplusB $end
$var parameter 32 5 W $end
$var reg 4 6 AluCtl [3:0] $end
$var reg 4 7 romAddr [3:0] $end
$var reg 1 8 romOE $end
$scope module alu $end
$var wire 4 9 ALUctl [3:0] $end
$var wire 32 : ALUout [31:0] $end
$var wire 32 ; B [31:0] $end
$var wire 1 < Zero $end
$var wire 1 = Overflow $end
$var wire 32 > A [31:0] $end
$var parameter 32 ? W $end
$var reg 32 @ outreg [31:0] $end
$upscope $end
$scope module rf $end
$var wire 32 A Data1 [31:0] $end
$var wire 32 B Data2 [31:0] $end
$var wire 5 C Read1 [4:0] $end
$var wire 5 D Read2 [4:0] $end
$var wire 1 $ RegWrite $end
$var wire 32 E WriteData [31:0] $end
$var wire 5 F WriteReg [4:0] $end
$var wire 1 # clock $end
$var parameter 32 G W $end
$upscope $end
$scope module rom $end
$var wire 4 H address [3:0] $end
$var wire 1 8 oe $end
$var wire 32 I data [31:0] $end
$var parameter 32 J L $end
$var parameter 32 K W $end
$upscope $end
$upscope $end
$upscope $end
$enddefinitions $end
$comment Show the parameter values. $end
$dumpall
b100000 K
b10000 J
b100000 G
b100000 ?
b100000 5
b10 4
b1 3
b1100 2
b110 1
b111 0
b0 /
b100000 "
$end
#0
$dumpvars
b100000000000000010011 I
b0 H
b0 F
b1 E
b1 D
b0 C
bx B
b0 A
b1 @
b0 >
0=
0<
b1 ;
b1 :
b10 9
18
b0 7
b10 6
b1 .
b1 -
b0 ,
bx +
b0 *
b100000000000000010011 )
b0 (
b0 '
1&
b0 %
0$
0#
b0 !
$end
#1
0&
1#
#2
0#
#3
1#
#4
1$
0#
#5
b1 F
b100000000000010010011 )
b100000000000010010011 I
b1 7
b1 H
1#
#6
0$
0#
#7
1$
1#
#8
0#
#9
b10 -
b10 :
b10 E
b10 @
b100001000000010110011 )
b100001000000010110011 I
b1 !
b1 '
b1 ,
b1 >
b1 A
b1 *
b1 C
b10 7
b10 H
b1 %
b1 (
0$
b1 +
b1 B
1#
#10
1$
0#
#11
b10 F
b0 D
b1000000100110011 )
b1000000100110011 I
b11 7
b11 H
b10 -
b10 :
b10 E
b10 @
b0 .
b0 ;
b10 !
b10 '
b10 ,
b10 >
b10 A
b0 +
b0 B
1#
#12
0$
0#
#13
1$
1#
#14
0#
#15
b100 -
b100 :
b100 E
b100 @
b10 .
b10 ;
b11 F
b10 +
b10 B
b10 D
b1000001000000110110011 )
b1000001000000110110011 I
b10 *
b10 C
b100 7
b100 H
b10 %
b10 (
0$
1#
#16
b1 *
b1 C
1$
0#
#17
b100 .
b100 ;
0<
b1 -
b1 :
b1 E
b1 @
b100 F
b100 +
b100 B
b11 D
b111 6
b111 9
b1100001010001000110011 )
b1100001010001000110011 I
b101 7
b101 H
1#
#18
1<
b0 -
b0 :
b0 E
b0 @
b100 !
b100 '
b100 ,
b100 >
b100 A
b11 *
b11 C
b11 %
b11 (
0$
0#
#19
0<
b1 -
b1 :
b1 E
b1 @
b10 !
b10 '
b10 ,
b10 >
b10 A
b1 *
b1 C
1$
1#
#20
0#
#21
1<
b1 .
b1 ;
b0 -
b0 :
b0 E
b0 @
b101 F
b1 +
b1 B
b100 D
b110 6
b110 9
b1000000010000011000001010110011 )
b1000000010000011000001010110011 I
b1 !
b1 '
b1 ,
b1 >
b1 A
b100 *
b100 C
b110 7
b110 H
b100 %
b100 (
0$
1#
#22
0<
b11 -
b11 :
b11 E
b11 @
b100 !
b100 '
b100 ,
b100 >
b100 A
b11 *
b11 C
1$
0#
#23
b100 .
b100 ;
b11 !
b11 '
b11 ,
b11 >
b11 A
b101 *
b101 C
b111 -
b111 :
b111 E
b111 @
b110 F
b100 +
b100 B
b11 D
b1 6
b1 9
b1100101110001100110011 )
b1100101110001100110011 I
b111 7
b111 H
1#
#24
b101 %
b101 (
0$
0#
#25
1$
1#
#26
0#
#27
b1 .
b1 ;
b1 -
b1 :
b1 E
b1 @
b111 F
b1 +
b1 B
b100 D
b0 6
b0 9
b10000101111001110110011 )
b10000101111001110110011 I
b111 !
b111 '
b111 ,
b111 >
b111 A
b110 *
b110 C
b1000 7
b1000 H
b110 %
b110 (
0$
1#
#28
b11 !
b11 '
b11 ,
b11 >
b11 A
b101 *
b101 C
1$
0#
#29
b1 !
b1 '
b1 ,
b1 >
b1 A
b111 *
b111 C
b111111111111 .
b111111111111 ;
b111111111111 -
b111111111111 :
b111111111111 E
b111111111111 @
bx +
bx B
b11111 D
b1 6
b1 9
b11111111111100111110001110010011 )
b11111111111100111110001110010011 I
b1001 7
b1001 H
1#
#30
b111 %
b111 (
0$
0#
#31
1$
1#
#32
0#
#33
b1 .
b1 ;
1<
b0 -
b0 :
b0 E
b0 @
b1000 F
b10 +
b10 B
b1 D
b111 6
b111 9
b100111010010000010011 )
b100111010010000010011 I
b1010 7
b1010 H
0$
b111111111111 !
b111111111111 '
b111111111111 ,
b111111111111 >
b111111111111 A
1#
#34
1$
0#
#35
0<
b1 -
b1 :
b1 E
b1 @
b1001 F
b0 6
b0 9
b100111111010010010011 )
b100111111010010010011 I
b1011 7
b1011 H
1#
#36
1<
b0 -
b0 :
b0 E
b0 @
b0 !
b0 '
b0 ,
b0 >
b0 A
b1000 *
b1000 C
b1000 %
b1000 (
0$
0#
#37
0<
b1 -
b1 :
b1 E
b1 @
b111111111111 !
b111111111111 '
b111111111111 ,
b111111111111 >
b111111111111 A
b111 *
b111 C
1$
1#
#38
0#
#39
b10 -
b10 :
b10 E
b10 @
b1010 F
b10 6
b10 9
b100111000010100010011 )
b100111000010100010011 I
b1 !
b1 '
b1 ,
b1 >
b1 A
b1001 *
b1001 C
b1100 7
b1100 H
b1001 %
b1001 (
0$
1#
#40
b1000000000000 -
b1000000000000 :
b1000000000000 E
b1000000000000 @
b111111111111 !
b111111111111 '
b111111111111 ,
b111111111111 >
b111111111111 A
b111 *
b111 C
1$
0#
#41
b1000000000001 -
b1000000000001 :
b1000000000001 E
b1000000000001 @
b1000000000000 !
b1000000000000 '
b1000000000000 ,
b1000000000000 >
b1000000000000 A
b1010 *
b1010 C
b0 F
b1 +
b1 B
b1001 D
b100101010000000000110011 )
b100101010000000000110011 I
b1101 7
b1101 H
1#
#42
b1010 %
b1010 (
0$
0#
#43
1$
1#
#44
0#
#45
b1010 F
b100101000000010100110011 )
b100101000000010100110011 I
b1110 7
b1110 H
0$
1#
#46
b1 -
b1 :
b1 E
b1 @
b0 !
b0 '
b0 ,
b0 >
b0 A
b1000 *
b1000 C
1$
0#
#47
b111111111111 .
b111111111111 ;
b1 !
b1 '
b1 ,
b1 >
b1 A
b1010 *
b1010 C
b11111111111111111111000000000010 -
b11111111111111111111000000000010 :
b11111111111111111111000000000010 E
b11111111111111111111000000000010 @
b111111111111 +
b111111111111 B
b111 D
b110 6
b110 9
b1000000011101010000010100110011 )
b1000000011101010000010100110011 I
b1111 7
b1111 H
1#
#48
0$
0#
#49
1$
1#
#50
0#
#51
b1 .
b1 ;
b0 F
b10 +
b10 B
b1 D
b10 6
b10 9
b100000000000000010011 )
b100000000000000010011 I
b0 7
b0 H
0$
b11111111111111111111000000000011 -
b11111111111111111111000000000011 :
b11111111111111111111000000000011 E
b11111111111111111111000000000011 @
b11111111111111111111000000000010 !
b11111111111111111111000000000010 '
b11111111111111111111000000000010 ,
b11111111111111111111000000000010 >
b11111111111111111111000000000010 A
1#
